pipeline_composer/__init__.py
pipeline_composer/cli.py
pipeline_composer/pipeline_composer.py
pipeline_composer-0.0.1.dist-info/AUTHORS.rst
pipeline_composer-0.0.1.dist-info/LICENSE
pipeline_composer-0.0.1.dist-info/METADATA
pipeline_composer-0.0.1.dist-info/WHEEL
pipeline_composer-0.0.1.dist-info/entry_points.txt
pipeline_composer-0.0.1.dist-info/top_level.txt
pipeline_composer-0.0.1.dist-info/RECORD
