Metadata-Version: 2.1
Name: pipeline-composer
Version: 0.0.1
Summary: Generate your CodeCommit/CodeBuild/CodePipeline templates made easier
Home-page: https://github.com/johnpreston/pipeline_composer
Author: John Preston
Author-email: john@lambda-my-aws.io
License: BSD license
Keywords: pipeline_composer
Platform: UNKNOWN
Classifier: Development Status :: 2 - Pre-Alpha
Classifier: Intended Audience :: Developers
Classifier: License :: OSI Approved :: BSD License
Classifier: Natural Language :: English
Classifier: Programming Language :: Python :: 3
Classifier: Programming Language :: Python :: 3.5
Classifier: Programming Language :: Python :: 3.6
Classifier: Programming Language :: Python :: 3.7
Classifier: Programming Language :: Python :: 3.8
Requires-Python: >=3.5
